{
    "id": "100864744599168697122",
    "displayName": "Ігор Булаєвський",
    "name": {
        "familyName": "Булаєвський",
        "givenName": "Ігор"
    },
    "emails": [
        {
            "value": "latente.traumgedanken@gmail.com",
            "type": "account"
        }
    ],
    "photos": [
        {
            "value": "https://lh3.googleusercontent.com/a-/AN66SAzHTRN3Gi-1qOcxBpSOFDm0mA8JVcwz2_ETS3xOnQ?sz=50"
        }
    ],
    "provider": "google",
    "_raw": "{\n \"kind\": \"plus#person\",\n \"etag\": \"\\\"jb1Xzanox6i8Zyse4DcYD8sZqy0/aH3AtS3Z9j99drUPSBUDOHjl2yw\\\"\",\n \"emails\": [\n  {\n   \"value\": \"latente.traumgedanken@gmail.com\",\n   \"type\": \"account\"\n  }\n ],\n \"objectType\": \"person\",\n \"id\": \"100864744599168697122\",\n \"displayName\": \"Ігор Булаєвський\",\n \"name\": {\n  \"familyName\": \"Булаєвський\",\n  \"givenName\": \"Ігор\"\n },\n \"url\": \"https://plus.google.com/100864744599168697122\",\n \"image\": {\n  \"url\": \"https://lh3.googleusercontent.com/a-/AN66SAzHTRN3Gi-1qOcxBpSOFDm0mA8JVcwz2_ETS3xOnQ?sz=50\",\n  \"isDefault\": false\n },\n \"isPlusUser\": true,\n \"circledByCount\": 0,\n \"verified\": false\n}\n",
    "_json": {
        "kind": "plus#person",
        "etag": "\"jb1Xzanox6i8Zyse4DcYD8sZqy0/aH3AtS3Z9j99drUPSBUDOHjl2yw\"",
        "emails": [
            {
                "value": "latente.traumgedanken@gmail.com",
                "type": "account"
            }
        ],
        "objectType": "person",
        "id": "100864744599168697122",
        "displayName": "Ігор Булаєвський",
        "name": {
            "familyName": "Булаєвський",
            "givenName": "Ігор"
        },
        "url": "https://plus.google.com/100864744599168697122",
        "image": {
            "url": "https://lh3.googleusercontent.com/a-/AN66SAzHTRN3Gi-1qOcxBpSOFDm0mA8JVcwz2_ETS3xOnQ?sz=50",
            "isDefault": false
        },
        "isPlusUser": true,
        "circledByCount": 0,
        "verified": false
    }
}